adafruit_pio_uart.py
adafruit_circuitpython_pio_uart-1.1.4.dist-info/licenses/LICENSE
adafruit_circuitpython_pio_uart-1.1.4.dist-info/METADATA
adafruit_circuitpython_pio_uart-1.1.4.dist-info/WHEEL
adafruit_circuitpython_pio_uart-1.1.4.dist-info/top_level.txt
adafruit_circuitpython_pio_uart-1.1.4.dist-info/RECORD
