Metadata-Version: 2.4
Name: adafruit-circuitpython-pio-uart
Version: 1.1.4
Summary: PIO implementation of CircuitPython UART API
Author-email: Adafruit Industries <circuitpython@adafruit.com>
License: MIT
Project-URL: Homepage, https://github.com/adafruit/Adafruit_CircuitPython_PIO_UART
Keywords: adafruit,blinka,circuitpython,micropython,pio_uart
Classifier: Intended Audience :: Developers
Classifier: Topic :: Software Development :: Libraries
Classifier: Topic :: Software Development :: Embedded Systems
Classifier: Topic :: System :: Hardware
Classifier: License :: OSI Approved :: MIT License
Classifier: Programming Language :: Python :: 3
License-File: LICENSE
Requires-Dist: Adafruit-Blinka
Requires-Dist: adafruit-circuitpython-pioasm
Provides-Extra: optional
Dynamic: license-file
